autopop/__init__.py
autopop/aspect_factory.py
autopop/ddb_util_wrapper.py
autopop/google_util_wrapper.py
autopop/knowledge_base.py
autopop-2.7.dist-info/METADATA
autopop-2.7.dist-info/WHEEL
autopop-2.7.dist-info/top_level.txt
autopop-2.7.dist-info/RECORD
