Metadata-Version: 2.1
Name: autopop
Version: 2.7
Summary: Auto Populate GDoc tables using LLMs.
Home-page: https://github.com/yourusername/yourrepository
Author: David Schwartz
Author-email: david.schwartz@devfactory.com
License: UNKNOWN
Platform: UNKNOWN
Classifier: Programming Language :: Python :: 3
Classifier: License :: OSI Approved :: MIT License
Classifier: Operating System :: OS Independent
Requires-Dist: boto3
Requires-Dist: requests
Requires-Dist: openai
Requires-Dist: anthropic
Requires-Dist: paper-qa
Requires-Dist: langchain
Requires-Dist: importlib
